{"cameraMode":{"drawMode":0,"name":"Shaded","section":"Shading Mode"},"sceneLighting":true,"audioPlay":false,"sceneViewState":{"m_AlwaysRefresh":false,"showFog":true,"showSkybox":true,"showFlares":true,"showImageEffects":true,"showParticleSystems":true,"showVisualEffectGraphs":true,"m_FxEnabled":true},"in2DMode":false,"pivot":{"x":-0.590534508228302,"y":-3.3605542182922365,"z":3.748861312866211},"rotation":{"x":0.3851548135280609,"y":-0.009689670987427235,"z":0.004044295754283667,"w":0.9227927923202515},"size":9.192862510681153,"orthographic":false}