{"cameraMode":{"drawMode":0,"name":"Shaded","section":"Shading Mode"},"sceneLighting":false,"audioPlay":false,"sceneViewState":{"m_AlwaysRefresh":false,"showFog":true,"showSkybox":false,"showFlares":true,"showImageEffects":true,"showParticleSystems":true,"showVisualEffectGraphs":true,"m_FxEnabled":true},"in2DMode":false,"pivot":{"x":-8.095353126525879,"y":2.2292943000793459,"z":11.869244575500489},"rotation":{"x":0.3604904115200043,"y":0.21106171607971192,"z":-0.08413834869861603,"w":0.9046953320503235},"size":0.7790116667747498,"orthographic":false}